[
  {
    "full_name": "jonghwanhyeon/python-stopwatch",
    "stargazers_count": 3,
    "open_issues_count": 0,
    "forks_count": 1
  },
  {
    "full_name": "elastic/eland",
    "stargazers_count": 400,
    "open_issues_count": 66,
    "forks_count": 53
  },
  {
    "full_name": "jsonresume/jsonresume-fake",
    "stargazers_count": 169,
    "open_issues_count": 3,
    "forks_count": 23
  },
  {
    "full_name": "fabfuel/ecs-deploy",
    "stargazers_count": 686,
    "open_issues_count": 38,
    "forks_count": 133
  },
  {
    "full_name": "awslabs/aws-lambda-rust-runtime",
    "stargazers_count": 2136,
    "open_issues_count": 8,
    "forks_count": 220
  },
  {
    "full_name": "mainframed/DC619",
    "stargazers_count": 9,
    "open_issues_count": 0,
    "forks_count": 0
  },
  {
    "full_name": "spec-first/connexion",
    "stargazers_count": 4026,
    "open_issues_count": 161,
    "forks_count": 708
  },
  {
    "full_name": "vladislav-e-martin/terrain-map-viewer",
    "stargazers_count": 1,
    "open_issues_count": 0,
    "forks_count": 0
  },
  {
    "full_name": "sonatype-nexus-community/jake",
    "stargazers_count": 65,
    "open_issues_count": 15,
    "forks_count": 17
  },
  {
    "full_name": "christiansandberg/pytest-reporter-html1",
    "stargazers_count": 14,
    "open_issues_count": 3,
    "forks_count": 3
  },
  {
    "full_name": "jhermann/rituals",
    "stargazers_count": 29,
    "open_issues_count": 24,
    "forks_count": 4
  },
  {
    "full_name": "matthewdeanmartin/pep541status",
    "stargazers_count": 1,
    "open_issues_count": 0,
    "forks_count": 0
  },
  {
    "full_name": "mcclure/NFTBlocker",
    "stargazers_count": 634,
    "open_issues_count": 3,
    "forks_count": 10
  },
  {
    "full_name": "pynamodb/PynamoDB",
    "stargazers_count": 1941,
    "open_issues_count": 258,
    "forks_count": 402
  },
  {
    "full_name": "opensearch-project/opensearch-dsl-py",
    "stargazers_count": 17,
    "open_issues_count": 12,
    "forks_count": 13
  },
  {
    "full_name": "en9inerd/telebuilder",
    "stargazers_count": 1,
    "open_issues_count": 0,
    "forks_count": 0
  },
  {
    "full_name": "rsyring/pyweb-flog2",
    "stargazers_count": 6,
    "open_issues_count": 2,
    "forks_count": 1
  },
  {
    "full_name": "fadyadal/putshebang",
    "stargazers_count": 1,
    "open_issues_count": 4,
    "forks_count": 0
  },
  {
    "full_name": "FHPythonUtils/PyTaintX",
    "stargazers_count": 2,
    "open_issues_count": 0,
    "forks_count": 0
  },
  {
    "full_name": "gophertuts/go-basics",
    "stargazers_count": 221,
    "open_issues_count": 0,
    "forks_count": 73
  },
  {
    "full_name": "opencontrol/compliance-masonry",
    "stargazers_count": 321,
    "open_issues_count": 40,
    "forks_count": 80
  },
  {
    "full_name": "bmustiata/jenny",
    "stargazers_count": 85,
    "open_issues_count": 6,
    "forks_count": 11
  },
  {
    "full_name": "adafruit/circuitpython",
    "stargazers_count": 3063,
    "open_issues_count": 550,
    "forks_count": 790
  },
  {
    "full_name": "robincamille/nondescript",
    "stargazers_count": 33,
    "open_issues_count": 0,
    "forks_count": 1
  },
  {
    "full_name": "jendrikseipp/vulture",
    "stargazers_count": 2147,
    "open_issues_count": 20,
    "forks_count": 105
  },
  {
    "full_name": "jan-Lope/toki-sin",
    "stargazers_count": 2,
    "open_issues_count": 3,
    "forks_count": 2
  },
  {
    "full_name": "justinsilvestre/parse-toki-pona",
    "stargazers_count": 3,
    "open_issues_count": 0,
    "forks_count": 0
  },
  {
    "full_name": "StackExchange/blackbox",
    "stargazers_count": 6267,
    "open_issues_count": 57,
    "forks_count": 360
  },
  {
    "full_name": "gwu-libraries/sfm-ui",
    "stargazers_count": 135,
    "open_issues_count": 87,
    "forks_count": 25
  },
  {
    "full_name": "nvbn/thefuck",
    "stargazers_count": 71946,
    "open_issues_count": 261,
    "forks_count": 3226
  }
]